DESCRIPTION
MANIFEST.in
README.rst
setup.py
bitmazk_contact_form.egg-info/PKG-INFO
bitmazk_contact_form.egg-info/SOURCES.txt
bitmazk_contact_form.egg-info/dependency_links.txt
bitmazk_contact_form.egg-info/requires.txt
bitmazk_contact_form.egg-info/top_level.txt
contact_form/__init__.py
contact_form/__init__.pyc
contact_form/admin.py
contact_form/admin.pyc
contact_form/cms_apps.py
contact_form/forms.py
contact_form/forms.pyc
contact_form/models.py
contact_form/models.pyc
contact_form/urls.py
contact_form/urls.pyc
contact_form/views.py
contact_form/views.pyc
contact_form/__pycache__/__init__.cpython-35.pyc
contact_form/__pycache__/admin.cpython-35.pyc
contact_form/__pycache__/forms.cpython-35.pyc
contact_form/__pycache__/models.cpython-35.pyc
contact_form/__pycache__/views.cpython-35.pyc
contact_form/locale/de/LC_MESSAGES/django.mo
contact_form/locale/de/LC_MESSAGES/django.po
contact_form/migrations/0001_initial.py
contact_form/migrations/0001_initial.pyc
contact_form/migrations/__init__.py
contact_form/migrations/__init__.pyc
contact_form/migrations/__pycache__/0001_initial.cpython-35.pyc
contact_form/migrations/__pycache__/__init__.cpython-35.pyc
contact_form/south_migrations/0001_initial.py
contact_form/south_migrations/0002_auto__del_field_contactformcategorytranslation_contact_form_category__.py
contact_form/south_migrations/__init__.py
contact_form/south_migrations/__pycache__/__init__.cpython-35.pyc
contact_form/static/contact_form/css/contact_form.css
contact_form/templates/contact_form.html
contact_form/templates/captcha/widget_nocaptcha.html
contact_form/templates/contact_form/contact_form.html
contact_form/templates/contact_form/contact_form_success.html
contact_form/templates/contact_form/email/contact_form.html
contact_form/templates/contact_form/email/contact_form_subject.html
contact_form/tests/__init__.py
contact_form/tests/__init__.pyc
contact_form/tests/forms_tests.py
contact_form/tests/forms_tests.pyc
contact_form/tests/models_tests.py
contact_form/tests/models_tests.pyc
contact_form/tests/settings.py
contact_form/tests/settings.pyc
contact_form/tests/test_settings.py
contact_form/tests/test_settings.pyc
contact_form/tests/urls.py
contact_form/tests/urls.pyc
