Metadata-Version: 1.0
Name: bitmazk-contact-form
Version: 1.3.1
Summary: A reusable contact form app for Django. Can be used with a modern user-friendly
